threatmon/__init__.py
threatmon/ioc.py
threatmon/utils.py
threatmon-0.4.0.dist-info/LICENCE.txt
threatmon-0.4.0.dist-info/METADATA
threatmon-0.4.0.dist-info/WHEEL
threatmon-0.4.0.dist-info/top_level.txt
threatmon-0.4.0.dist-info/RECORD
