Metadata-Version: 2.1
Name: threatmon
Version: 0.4.0
Summary: Cyber Security Framework for Python by Threatmon
Home-page: https://threatmon.io/
Author: Nurettin Sinanoğlu
Author-email: nurettin.sinanogluu@gmail.com
License: MIT
License-File: LICENCE.txt
Requires-Dist: numpy
Requires-Dist: progressbar
Requires-Dist: requests
Requires-Dist: pillow
Requires-Dist: imutils
Requires-Dist: OTXv2
Requires-Dist: pan-os-python
Requires-Dist: termcolor
Requires-Dist: stix2
